dash_spa/__init__.py
dash_spa/_version.py
dash_spa/callback.py
dash_spa/context_state.py
dash_spa/decorators.py
dash_spa/exceptions.py
dash_spa/logging.py
dash_spa/spa_config.py
dash_spa/spa_context.py
dash_spa/spa_current_app.py
dash_spa/spa_current_user.py
dash_spa/spa_form.py
dash_spa/spa_globals.py
dash_spa/spa_pages.py
dash_spa/components/AIO_base.py
dash_spa/components/StoreState.py
dash_spa/components/__init__.py
dash_spa/components/alert.py
dash_spa/components/button_container_aoi.py
dash_spa/components/dropdown_aio.py
dash_spa/components/dropdown_button_aoi.py
dash_spa/components/dropdown_folder_aoi.py
dash_spa/components/footer.py
dash_spa/components/icons.py
dash_spa/components/navbar.py
dash_spa/components/notyf.py
dash_spa/components/spa_location.py
dash_spa/components/store_aio.py
dash_spa/components/table/__init__.py
dash_spa/components/table/context.py
dash_spa/components/table/icons.py
dash_spa/components/table/pagination_aoi.py
dash_spa/components/table/pagination_view_aoi.py
dash_spa/components/table/search.py
dash_spa/components/table/table_aio.py
dash_spa/plugins/__init__.py
dash_spa/plugins/dash_logging.py
dash_spa/session/__init__.py
dash_spa/session/session_cookie.py
dash_spa/session/session_data.py
dash_spa/session/backends/__init__.py
dash_spa/session/backends/backend_factory.py
dash_spa/session/backends/diskcache.py
dash_spa/session/backends/postgres.py
dash_spa/session/backends/redis.py
dash_spa/session/backends/session_backend.py
dash_spa/utils/__init__.py
dash_spa/utils/caller.py
dash_spa/utils/dataclass.py
dash_spa/utils/dumps_layout.py
dash_spa/utils/json_coder.py
dash_spa/utils/notify_dict.py
dash_spa/utils/syncronised.py
dash_spa/utils/time.py
dash_spa_admin/__init__.py
dash_spa_admin/admin_navbar.py
dash_spa_admin/admin_page.py
dash_spa_admin/decorators.py
dash_spa_admin/exceptions.py
dash_spa_admin/login_manager.py
dash_spa_admin/synchronised_cache.py
dash_spa_admin/template_mailer.py
dash_spa_admin/views/__init__.py
dash_spa-1.1.5.dist-info/LICENSE
dash_spa-1.1.5.dist-info/METADATA
dash_spa-1.1.5.dist-info/WHEEL
dash_spa-1.1.5.dist-info/top_level.txt
dash_spa-1.1.5.dist-info/RECORD
