Metadata-Version: 2.1
Name: dash-spa
Version: 1.1.5
Summary: Dash Pages SPA Framework
Home-page: https://github.com/stevej2608/dash-spa
Author: Steve Jones
Author-email: jonesst608@gmail.com
License: MIT
Classifier: Environment :: Web Environment
Classifier: Framework :: Dash
Classifier: Programming Language :: Python
Classifier: Programming Language :: Python :: 3
Classifier: Programming Language :: Python :: 3.6
Classifier: Programming Language :: Python :: 3.7
Classifier: Programming Language :: Python :: 3.8
Classifier: Programming Language :: Python :: 3.9
Requires-Python: >=3.6
License-File: LICENSE
Requires-Dist: dash-bootstrap-components (>=1.1.0)
Requires-Dist: dash-holoniq-components (>=0.0.19)
Requires-Dist: dash-prefix (>=0.0.4)
Requires-Dist: dash-redux (>=0.0.4)
Requires-Dist: dash-svg (>=0.0.8)
Requires-Dist: dash (>=2.1.0)
Requires-Dist: iniconfig (>=1.1.1)
Requires-Dist: appdirs (>=1.4.4)
Requires-Dist: itsdangerous (>=2.0.1)
Provides-Extra: admin
Requires-Dist: Werkzeug (==2.1.2) ; extra == 'admin'
Requires-Dist: cachetools (>=5.0.0) ; extra == 'admin'
Requires-Dist: dash-datatables (>=0.0.9) ; extra == 'admin'
Requires-Dist: Flask-Login (>=0.4.1) ; extra == 'admin'
Requires-Dist: Flask-SQLAlchemy (>=2.5.1) ; extra == 'admin'
Requires-Dist: pystache (>=0.6.0) ; extra == 'admin'
Requires-Dist: SQLAlchemy-Utils (>=0.38.2) ; extra == 'admin'
Provides-Extra: dev
Requires-Dist: dash[testing] (>=2.1.0) ; extra == 'dev'
Requires-Dist: keyrings.alt (>=4.1.0) ; extra == 'dev'
Requires-Dist: pytest-env (>=0.6.2) ; extra == 'dev'
Requires-Dist: pytest-mock (>=3.7.0) ; extra == 'dev'
Requires-Dist: pytest (>=7.1.1) ; extra == 'dev'
Requires-Dist: selenium (>=4.1.0) ; extra == 'dev'
Requires-Dist: setuptools (>=63.2.0) ; extra == 'dev'
Requires-Dist: twine (==3.7.1) ; extra == 'dev'
Provides-Extra: diskcache
Requires-Dist: diskcache (>=5.4.0) ; extra == 'diskcache'
Provides-Extra: redis
Requires-Dist: redis (>=4.3.4) ; extra == 'redis'
